hypmaps/__init__.py
hypmaps/poincare.py
hypmaps-0.0.1.dist-info/LICENSE
hypmaps-0.0.1.dist-info/METADATA
hypmaps-0.0.1.dist-info/WHEEL
hypmaps-0.0.1.dist-info/top_level.txt
hypmaps-0.0.1.dist-info/RECORD
